{
    "full_name": "GrowingGit/GitHub-Chinese-Top-Charts",
    "name": "GitHub-Chinese-Top-Charts",
    "html_url": "https://github.com/GrowingGit/GitHub-Chinese-Top-Charts",
    "stargazers_count": 51813,
    "language": "Java",
    "description": "\ud83c\udde8\ud83c\uddf3 GitHub\u4e2d\u6587\u6392\u884c\u699c\uff0c\u5404\u8bed\u8a00\u5206\u8bbe\u300c\u8f6f\u4ef6 | \u8d44\u6599\u300d\u699c\u5355\uff0c\u7cbe\u51c6\u5b9a\u4f4d\u4e2d\u6587\u597d\u9879\u76ee\u3002\u5404\u53d6\u6240\u9700\uff0c\u9ad8\u6548\u5b66\u4e60\u3002",
    "date_range": "39 stars today",
    "watchers_count": -1
}